defectdojo/__init__.py
defectdojo/client.py
defectdojo/engagements_tools.py
defectdojo/findings_tools.py
defectdojo/products_tools.py
defectdojo/tools.py
defectdojo_mcp-0.1.2.dist-info/licenses/LICENSE
defectdojo_mcp-0.1.2.dist-info/METADATA
defectdojo_mcp-0.1.2.dist-info/WHEEL
defectdojo_mcp-0.1.2.dist-info/entry_points.txt
defectdojo_mcp-0.1.2.dist-info/top_level.txt
defectdojo_mcp-0.1.2.dist-info/RECORD
